Workbook

Sheet Comece aqui
B2: Calculadora do Seu Número
B3: Descubra quanto é a sua reserva e quanto guardar por mês para chegar lá.
B5: 1 | C5: Vá na aba 1 · Despesas e preencha as células AMARELAS com o valor mensal de cada despesa essencial.
B6: 2 | C6: Vá na aba 2 · Seu Número. Confira quantos meses de reserva você quer (padrão: 6), em quantos meses quer chegar lá (padrão: 18) e quanto já tem guardado.
B7: 3 | C7: Pronto: a planilha mostra o seu número e quanto guardar por mês e por semana. Mude o prazo e o valor mensal muda na hora.
B8: 4 | C8: Todo mês, vá na aba 3 · Acompanhamento e anote quanto depositou. A planilha mostra quanto já juntou, quanto falta e se você está no ritmo.
B9: 5 | C9: A aba 4 · Simulador de prazo compara quanto guardar por mês em prazos de 6 a 36 meses.
C11: Só preencha as células AMARELAS. As outras têm fórmulas e estão protegidas para você não apagar sem querer.
C13: Funciona no Excel, no Google Planilhas (Arquivo → Importar) e no LibreOffice. No celular, use o app do Google Planilhas ou do Excel.
C14: Conteúdo educativo. Valores sem considerar rendimento; confira as regras vigentes do lugar onde você guarda o dinheiro.

Sheet 1 · Despesas
B2: Suas despesas essenciais
B3: Valores MENSAIS. Conta anual? Divida por 12. Use extratos reais dos últimos 3 meses.
B5: DESPESA ESSENCIAL
B6: Moradia (aluguel ou financiamento, condomínio) | E6: O que entra aqui?
B7: Contas de casa (luz, água, gás) | E7: Só o que você NÃO pode deixar de pagar nem por um mês.
B8: Internet e celular (plano básico) | E8: Fica de fora: delivery, streaming, roupas, saídas,
B9: Alimentação (mercado, sem delivery) | E9: compras parceladas não essenciais.
B10: Transporte (para trabalhar ou procurar trabalho)
B11: Saúde (plano, remédios de uso contínuo) | E11: Os nomes das linhas "Outro essencial" podem ser
B12: Educação obrigatória (escola dos filhos) | E12: editados: clique e escreva o que for.
B13: Dívidas que não podem atrasar (parcelas)
B14: Outro essencial 1
B15: Outro essencial 2
B16: Outro essencial 3
B17: CUSTO ESSENCIAL MENSAL | C17: =SUM(C6:C16)

Sheet 2 · Seu Número
B2: Seu número
B3: Ajuste os campos amarelos. Todo o resto é calculado na hora.
B5: SEUS DADOS
B6: Custo essencial mensal (vem da aba 1) | C6: ='1 · Despesas'!C17 | E6: Como ler
B7: Quantos meses de reserva você quer? | C7: 6 | E7: Seu número = custo essencial × meses de reserva.
B8: Em quantos meses quer chegar lá? (prazo) | C8: 18 | E8: Guardar por mês = (seu número − o que já tem) ÷ prazo.
B9: Quanto você já tem guardado hoje? | C9: 0
E10: O valor mensal não cabe no seu orçamento?
B11: RESULTADO | E11: Aumente o prazo no campo amarelo e veja o novo valor.
B12: SEU NÚMERO (meta da reserva) | C12: =C6*C7 | E12: Ou compare vários prazos na aba 4 · Simulador de prazo.
B13: Quanto ainda falta | C13: =MAX(C12-C9,0)
B14: GUARDAR POR MÊS | C14: =IF(C8>0,C13/C8,0) | E14: Os valores não consideram rendimento: na prática,
B15: Guardar por semana (aprox.) | C15: =C14*12/52 | E15: o dinheiro aplicado rende e você chega um pouco antes.
B16: Guardar por dia (aprox.) | C16: =C14*12/365
B17: Você já tem quantos meses de reserva? | C17: =IF(C6>0,C9/C6,0)
B19: SEUS DEGRAUS
B20: Degrau 1 · R$ 1.000 ou meio mês (o menor) | C20: =MIN(1000,C6/2)
B21: Degrau 2 · 1 mês de custo essencial | C21: =C6*1
B22: Degrau 3 · 3 meses de custo essencial | C22: =C6*3
B23: Degrau 4 · reserva completa | C23: =C12

Sheet 3 · Acompanhamento
B2: Acompanhamento mês a mês
B3: Todo mês, anote na coluna amarela quanto você depositou. Se precisou sacar, anote com sinal de menos.
B4: Já tinha guardado: | D4: ='2 · Seu Número'!C9 | E4: Meta final: | F4: ='2 · Seu Número'!C12
B6: Mês | C6: Depositei no mês | D6: Total guardado | E6: Meta até aqui | F6: Diferença | G6: Quanto falta | H6: Situação
B7: 1 | D7: =IF(1<='2 · Seu Número'!$C$8,$D$4+SUM($C$7:C7),"") | E7: =IF(1<='2 · Seu Número'!$C$8,$D$4+'2 · Seu Número'!$C$14*B7,"") | F7: =IF(1<='2 · Seu Número'!$C$8,D7-E7,"") | G7: =IF(1<='2 · Seu Número'!$C$8,MAX($F$4-D7,0),"") | H7: =IF(1<='2 · Seu Número'!$C$8,IF(C7="","",IF(D7>=$F$4,"Reserva completa!",IF(F7>=0,"No ritmo","Abaixo da meta"))),"")
B8: 2 | D8: =IF(2<='2 · Seu Número'!$C$8,$D$4+SUM($C$7:C8),"") | E8: =IF(2<='2 · Seu Número'!$C$8,$D$4+'2 · Seu Número'!$C$14*B8,"") | F8: =IF(2<='2 · Seu Número'!$C$8,D8-E8,"") | G8: =IF(2<='2 · Seu Número'!$C$8,MAX($F$4-D8,0),"") | H8: =IF(2<='2 · Seu Número'!$C$8,IF(C8="","",IF(D8>=$F$4,"Reserva completa!",IF(F8>=0,"No ritmo","Abaixo da meta"))),"")
B9: 3 | D9: =IF(3<='2 · Seu Número'!$C$8,$D$4+SUM($C$7:C9),"") | E9: =IF(3<='2 · Seu Número'!$C$8,$D$4+'2 · Seu Número'!$C$14*B9,"") | F9: =IF(3<='2 · Seu Número'!$C$8,D9-E9,"") | G9: =IF(3<='2 · Seu Número'!$C$8,MAX($F$4-D9,0),"") | H9: =IF(3<='2 · Seu Número'!$C$8,IF(C9="","",IF(D9>=$F$4,"Reserva completa!",IF(F9>=0,"No ritmo","Abaixo da meta"))),"")
B10: 4 | D10: =IF(4<='2 · Seu Número'!$C$8,$D$4+SUM($C$7:C10),"") | E10: =IF(4<='2 · Seu Número'!$C$8,$D$4+'2 · Seu Número'!$C$14*B10,"") | F10: =IF(4<='2 · Seu Número'!$C$8,D10-E10,"") | G10: =IF(4<='2 · Seu Número'!$C$8,MAX($F$4-D10,0),"") | H10: =IF(4<='2 · Seu Número'!$C$8,IF(C10="","",IF(D10>=$F$4,"Reserva completa!",IF(F10>=0,"No ritmo","Abaixo da meta"))),"")
B11: 5 | D11: =IF(5<='2 · Seu Número'!$C$8,$D$4+SUM($C$7:C11),"") | E11: =IF(5<='2 · Seu Número'!$C$8,$D$4+'2 · Seu Número'!$C$14*B11,"") | F11: =IF(5<='2 · Seu Número'!$C$8,D11-E11,"") | G11: =IF(5<='2 · Seu Número'!$C$8,MAX($F$4-D11,0),"") | H11: =IF(5<='2 · Seu Número'!$C$8,IF(C11="","",IF(D11>=$F$4,"Reserva completa!",IF(F11>=0,"No ritmo","Abaixo da meta"))),"")
B12: 6 | D12: =IF(6<='2 · Seu Número'!$C$8,$D$4+SUM($C$7:C12),"") | E12: =IF(6<='2 · Seu Número'!$C$8,$D$4+'2 · Seu Número'!$C$14*B12,"") | F12: =IF(6<='2 · Seu Número'!$C$8,D12-E12,"") | G12: =IF(6<='2 · Seu Número'!$C$8,MAX($F$4-D12,0),"") | H12: =IF(6<='2 · Seu Número'!$C$8,IF(C12="","",IF(D12>=$F$4,"Reserva completa!",IF(F12>=0,"No ritmo","Abaixo da meta"))),"")
B13: 7 | D13: =IF(7<='2 · Seu Número'!$C$8,$D$4+SUM($C$7:C13),"") | E13: =IF(7<='2 · Seu Número'!$C$8,$D$4+'2 · Seu Número'!$C$14*B13,"") | F13: =IF(7<='2 · Seu Número'!$C$8,D13-E13,"") | G13: =IF(7<='2 · Seu Número'!$C$8,MAX($F$4-D13,0),"") | H13: =IF(7<='2 · Seu Número'!$C$8,IF(C13="","",IF(D13>=$F$4,"Reserva completa!",IF(F13>=0,"No ritmo","Abaixo da meta"))),"")
B14: 8 | D14: =IF(8<='2 · Seu Número'!$C$8,$D$4+SUM($C$7:C14),"") | E14: =IF(8<='2 · Seu Número'!$C$8,$D$4+'2 · Seu Número'!$C$14*B14,"") | F14: =IF(8<='2 · Seu Número'!$C$8,D14-E14,"") | G14: =IF(8<='2 · Seu Número'!$C$8,MAX($F$4-D14,0),"") | H14: =IF(8<='2 · Seu Número'!$C$8,IF(C14="","",IF(D14>=$F$4,"Reserva completa!",IF(F14>=0,"No ritmo","Abaixo da meta"))),"")
B15: 9 | D15: =IF(9<='2 · Seu Número'!$C$8,$D$4+SUM($C$7:C15),"") | E15: =IF(9<='2 · Seu Número'!$C$8,$D$4+'2 · Seu Número'!$C$14*B15,"") | F15: =IF(9<='2 · Seu Número'!$C$8,D15-E15,"") | G15: =IF(9<='2 · Seu Número'!$C$8,MAX($F$4-D15,0),"") | H15: =IF(9<='2 · Seu Número'!$C$8,IF(C15="","",IF(D15>=$F$4,"Reserva completa!",IF(F15>=0,"No ritmo","Abaixo da meta"))),"")
B16: 10 | D16: =IF(10<='2 · Seu Número'!$C$8,$D$4+SUM($C$7:C16),"") | E16: =IF(10<='2 · Seu Número'!$C$8,$D$4+'2 · Seu Número'!$C$14*B16,"") | F16: =IF(10<='2 · Seu Número'!$C$8,D16-E16,"") | G16: =IF(10<='2 · Seu Número'!$C$8,MAX($F$4-D16,0),"") | H16: =IF(10<='2 · Seu Número'!$C$8,IF(C16="","",IF(D16>=$F$4,"Reserva completa!",IF(F16>=0,"No ritmo","Abaixo da meta"))),"")
B17: 11 | D17: =IF(11<='2 · Seu Número'!$C$8,$D$4+SUM($C$7:C17),"") | E17: =IF(11<='2 · Seu Número'!$C$8,$D$4+'2 · Seu Número'!$C$14*B17,"") | F17: =IF(11<='2 · Seu Número'!$C$8,D17-E17,"") | G17: =IF(11<='2 · Seu Número'!$C$8,MAX($F$4-D17,0),"") | H17: =IF(11<='2 · Seu Número'!$C$8,IF(C17="","",IF(D17>=$F$4,"Reserva completa!",IF(F17>=0,"No ritmo","Abaixo da meta"))),"")
B18: 12 | D18: =IF(12<='2 · Seu Número'!$C$8,$D$4+SUM($C$7:C18),"") | E18: =IF(12<='2 · Seu Número'!$C$8,$D$4+'2 · Seu Número'!$C$14*B18,"") | F18: =IF(12<='2 · Seu Número'!$C$8,D18-E18,"") | G18: =IF(12<='2 · Seu Número'!$C$8,MAX($F$4-D18,0),"") | H18: =IF(12<='2 · Seu Número'!$C$8,IF(C18="","",IF(D18>=$F$4,"Reserva completa!",IF(F18>=0,"No ritmo","Abaixo da meta"))),"")
B19: 13 | D19: =IF(13<='2 · Seu Número'!$C$8,$D$4+SUM($C$7:C19),"") | E19: =IF(13<='2 · Seu Número'!$C$8,$D$4+'2 · Seu Número'!$C$14*B19,"") | F19: =IF(13<='2 · Seu Número'!$C$8,D19-E19,"") | G19: =IF(13<='2 · Seu Número'!$C$8,MAX($F$4-D19,0),"") | H19: =IF(13<='2 · Seu Número'!$C$8,IF(C19="","",IF(D19>=$F$4,"Reserva completa!",IF(F19>=0,"No ritmo","Abaixo da meta"))),"")
B20: 14 | D20: =IF(14<='2 · Seu Número'!$C$8,$D$4+SUM($C$7:C20),"") | E20: =IF(14<='2 · Seu Número'!$C$8,$D$4+'2 · Seu Número'!$C$14*B20,"") | F20: =IF(14<='2 · Seu Número'!$C$8,D20-E20,"") | G20: =IF(14<='2 · Seu Número'!$C$8,MAX($F$4-D20,0),"") | H20: =IF(14<='2 · Seu Número'!$C$8,IF(C20="","",IF(D20>=$F$4,"Reserva completa!",IF(F20>=0,"No ritmo","Abaixo da meta"))),"")
B21: 15 | D21: =IF(15<='2 · Seu Número'!$C$8,$D$4+SUM($C$7:C21),"") | E21: =IF(15<='2 · Seu Número'!$C$8,$D$4+'2 · Seu Número'!$C$14*B21,"") | F21: =IF(15<='2 · Seu Número'!$C$8,D21-E21,"") | G21: =IF(15<='2 · Seu Número'!$C$8,MAX($F$4-D21,0),"") | H21: =IF(15<='2 · Seu Número'!$C$8,IF(C21="","",IF(D21>=$F$4,"Reserva completa!",IF(F21>=0,"No ritmo","Abaixo da meta"))),"")
B22: 16 | D22: =IF(16<='2 · Seu Número'!$C$8,$D$4+SUM($C$7:C22),"") | E22: =IF(16<='2 · Seu Número'!$C$8,$D$4+'2 · Seu Número'!$C$14*B22,"") | F22: =IF(16<='2 · Seu Número'!$C$8,D22-E22,"") | G22: =IF(16<='2 · Seu Número'!$C$8,MAX($F$4-D22,0),"") | H22: =IF(16<='2 · Seu Número'!$C$8,IF(C22="","",IF(D22>=$F$4,"Reserva completa!",IF(F22>=0,"No ritmo","Abaixo da meta"))),"")
B23: 17 | D23: =IF(17<='2 · Seu Número'!$C$8,$D$4+SUM($C$7:C23),"") | E23: =IF(17<='2 · Seu Número'!$C$8,$D$4+'2 · Seu Número'!$C$14*B23,"") | F23: =IF(17<='2 · Seu Número'!$C$8,D23-E23,"") | G23: =IF(17<='2 · Seu Número'!$C$8,MAX($F$4-D23,0),"") | H23: =IF(17<='2 · Seu Número'!$C$8,IF(C23="","",IF(D23>=$F$4,"Reserva completa!",IF(F23>=0,"No ritmo","Abaixo da meta"))),"")
B24: 18 | D24: =IF(18<='2 · Seu Número'!$C$8,$D$4+SUM($C$7:C24),"") | E24: =IF(18<='2 · Seu Número'!$C$8,$D$4+'2 · Seu Número'!$C$14*B24,"") | F24: =IF(18<='2 · Seu Número'!$C$8,D24-E24,"") | G24: =IF(18<='2 · Seu Número'!$C$8,MAX($F$4-D24,0),"") | H24: =IF(18<='2 · Seu Número'!$C$8,IF(C24="","",IF(D24>=$F$4,"Reserva completa!",IF(F24>=0,"No ritmo","Abaixo da meta"))),"")
B25: 19 | D25: =IF(19<='2 · Seu Número'!$C$8,$D$4+SUM($C$7:C25),"") | E25: =IF(19<='2 · Seu Número'!$C$8,$D$4+'2 · Seu Número'!$C$14*B25,"") | F25: =IF(19<='2 · Seu Número'!$C$8,D25-E25,"") | G25: =IF(19<='2 · Seu Número'!$C$8,MAX($F$4-D25,0),"") | H25: =IF(19<='2 · Seu Número'!$C$8,IF(C25="","",IF(D25>=$F$4,"Reserva completa!",IF(F25>=0,"No ritmo","Abaixo da meta"))),"")
B26: 20 | D26: =IF(20<='2 · Seu Número'!$C$8,$D$4+SUM($C$7:C26),"") | E26: =IF(20<='2 · Seu Número'!$C$8,$D$4+'2 · Seu Número'!$C$14*B26,"") | F26: =IF(20<='2 · Seu Número'!$C$8,D26-E26,"") | G26: =IF(20<='2 · Seu Número'!$C$8,MAX($F$4-D26,0),"") | H26: =IF(20<='2 · Seu Número'!$C$8,IF(C26="","",IF(D26>=$F$4,"Reserva completa!",IF(F26>=0,"No ritmo","Abaixo da meta"))),"")
B27: 21 | D27: =IF(21<='2 · Seu Número'!$C$8,$D$4+SUM($C$7:C27),"") | E27: =IF(21<='2 · Seu Número'!$C$8,$D$4+'2 · Seu Número'!$C$14*B27,"") | F27: =IF(21<='2 · Seu Número'!$C$8,D27-E27,"") | G27: =IF(21<='2 · Seu Número'!$C$8,MAX($F$4-D27,0),"") | H27: =IF(21<='2 · Seu Número'!$C$8,IF(C27="","",IF(D27>=$F$4,"Reserva completa!",IF(F27>=0,"No ritmo","Abaixo da meta"))),"")
B28: 22 | D28: =IF(22<='2 · Seu Número'!$C$8,$D$4+SUM($C$7:C28),"") | E28: =IF(22<='2 · Seu Número'!$C$8,$D$4+'2 · Seu Número'!$C$14*B28,"") | F28: =IF(22<='2 · Seu Número'!$C$8,D28-E28,"") | G28: =IF(22<='2 · Seu Número'!$C$8,MAX($F$4-D28,0),"") | H28: =IF(22<='2 · Seu Número'!$C$8,IF(C28="","",IF(D28>=$F$4,"Reserva completa!",IF(F28>=0,"No ritmo","Abaixo da meta"))),"")
B29: 23 | D29: =IF(23<='2 · Seu Número'!$C$8,$D$4+SUM($C$7:C29),"") | E29: =IF(23<='2 · Seu Número'!$C$8,$D$4+'2 · Seu Número'!$C$14*B29,"") | F29: =IF(23<='2 · Seu Número'!$C$8,D29-E29,"") | G29: =IF(23<='2 · Seu Número'!$C$8,MAX($F$4-D29,0),"") | H29: =IF(23<='2 · Seu Número'!$C$8,IF(C29="","",IF(D29>=$F$4,"Reserva completa!",IF(F29>=0,"No ritmo","Abaixo da meta"))),"")
B30: 24 | D30: =IF(24<='2 · Seu Número'!$C$8,$D$4+SUM($C$7:C30),"") | E30: =IF(24<='2 · Seu Número'!$C$8,$D$4+'2 · Seu Número'!$C$14*B30,"") | F30: =IF(24<='2 · Seu Número'!$C$8,D30-E30,"") | G30: =IF(24<='2 · Seu Número'!$C$8,MAX($F$4-D30,0),"") | H30: =IF(24<='2 · Seu Número'!$C$8,IF(C30="","",IF(D30>=$F$4,"Reserva completa!",IF(F30>=0,"No ritmo","Abaixo da meta"))),"")
B31: 25 | D31: =IF(25<='2 · Seu Número'!$C$8,$D$4+SUM($C$7:C31),"") | E31: =IF(25<='2 · Seu Número'!$C$8,$D$4+'2 · Seu Número'!$C$14*B31,"") | F31: =IF(25<='2 · Seu Número'!$C$8,D31-E31,"") | G31: =IF(25<='2 · Seu Número'!$C$8,MAX($F$4-D31,0),"") | H31: =IF(25<='2 · Seu Número'!$C$8,IF(C31="","",IF(D31>=$F$4,"Reserva completa!",IF(F31>=0,"No ritmo","Abaixo da meta"))),"")
B32: 26 | D32: =IF(26<='2 · Seu Número'!$C$8,$D$4+SUM($C$7:C32),"") | E32: =IF(26<='2 · Seu Número'!$C$8,$D$4+'2 · Seu Número'!$C$14*B32,"") | F32: =IF(26<='2 · Seu Número'!$C$8,D32-E32,"") | G32: =IF(26<='2 · Seu Número'!$C$8,MAX($F$4-D32,0),"") | H32: =IF(26<='2 · Seu Número'!$C$8,IF(C32="","",IF(D32>=$F$4,"Reserva completa!",IF(F32>=0,"No ritmo","Abaixo da meta"))),"")
B33: 27 | D33: =IF(27<='2 · Seu Número'!$C$8,$D$4+SUM($C$7:C33),"") | E33: =IF(27<='2 · Seu Número'!$C$8,$D$4+'2 · Seu Número'!$C$14*B33,"") | F33: =IF(27<='2 · Seu Número'!$C$8,D33-E33,"") | G33: =IF(27<='2 · Seu Número'!$C$8,MAX($F$4-D33,0),"") | H33: =IF(27<='2 · Seu Número'!$C$8,IF(C33="","",IF(D33>=$F$4,"Reserva completa!",IF(F33>=0,"No ritmo","Abaixo da meta"))),"")
B34: 28 | D34: =IF(28<='2 · Seu Número'!$C$8,$D$4+SUM($C$7:C34),"") | E34: =IF(28<='2 · Seu Número'!$C$8,$D$4+'2 · Seu Número'!$C$14*B34,"") | F34: =IF(28<='2 · Seu Número'!$C$8,D34-E34,"") | G34: =IF(28<='2 · Seu Número'!$C$8,MAX($F$4-D34,0),"") | H34: =IF(28<='2 · Seu Número'!$C$8,IF(C34="","",IF(D34>=$F$4,"Reserva completa!",IF(F34>=0,"No ritmo","Abaixo da meta"))),"")
B35: 29 | D35: =IF(29<='2 · Seu Número'!$C$8,$D$4+SUM($C$7:C35),"") | E35: =IF(29<='2 · Seu Número'!$C$8,$D$4+'2 · Seu Número'!$C$14*B35,"") | F35: =IF(29<='2 · Seu Número'!$C$8,D35-E35,"") | G35: =IF(29<='2 · Seu Número'!$C$8,MAX($F$4-D35,0),"") | H35: =IF(29<='2 · Seu Número'!$C$8,IF(C35="","",IF(D35>=$F$4,"Reserva completa!",IF(F35>=0,"No ritmo","Abaixo da meta"))),"")
B36: 30 | D36: =IF(30<='2 · Seu Número'!$C$8,$D$4+SUM($C$7:C36),"") | E36: =IF(30<='2 · Seu Número'!$C$8,$D$4+'2 · Seu Número'!$C$14*B36,"") | F36: =IF(30<='2 · Seu Número'!$C$8,D36-E36,"") | G36: =IF(30<='2 · Seu Número'!$C$8,MAX($F$4-D36,0),"") | H36: =IF(30<='2 · Seu Número'!$C$8,IF(C36="","",IF(D36>=$F$4,"Reserva completa!",IF(F36>=0,"No ritmo","Abaixo da meta"))),"")
B37: 31 | D37: =IF(31<='2 · Seu Número'!$C$8,$D$4+SUM($C$7:C37),"") | E37: =IF(31<='2 · Seu Número'!$C$8,$D$4+'2 · Seu Número'!$C$14*B37,"") | F37: =IF(31<='2 · Seu Número'!$C$8,D37-E37,"") | G37: =IF(31<='2 · Seu Número'!$C$8,MAX($F$4-D37,0),"") | H37: =IF(31<='2 · Seu Número'!$C$8,IF(C37="","",IF(D37>=$F$4,"Reserva completa!",IF(F37>=0,"No ritmo","Abaixo da meta"))),"")
B38: 32 | D38: =IF(32<='2 · Seu Número'!$C$8,$D$4+SUM($C$7:C38),"") | E38: =IF(32<='2 · Seu Número'!$C$8,$D$4+'2 · Seu Número'!$C$14*B38,"") | F38: =IF(32<='2 · Seu Número'!$C$8,D38-E38,"") | G38: =IF(32<='2 · Seu Número'!$C$8,MAX($F$4-D38,0),"") | H38: =IF(32<='2 · Seu Número'!$C$8,IF(C38="","",IF(D38>=$F$4,"Reserva completa!",IF(F38>=0,"No ritmo","Abaixo da meta"))),"")
B39: 33 | D39: =IF(33<='2 · Seu Número'!$C$8,$D$4+SUM($C$7:C39),"") | E39: =IF(33<='2 · Seu Número'!$C$8,$D$4+'2 · Seu Número'!$C$14*B39,"") | F39: =IF(33<='2 · Seu Número'!$C$8,D39-E39,"") | G39: =IF(33<='2 · Seu Número'!$C$8,MAX($F$4-D39,0),"") | H39: =IF(33<='2 · Seu Número'!$C$8,IF(C39="","",IF(D39>=$F$4,"Reserva completa!",IF(F39>=0,"No ritmo","Abaixo da meta"))),"")
B40: 34 | D40: =IF(34<='2 · Seu Número'!$C$8,$D$4+SUM($C$7:C40),"") | E40: =IF(34<='2 · Seu Número'!$C$8,$D$4+'2 · Seu Número'!$C$14*B40,"") | F40: =IF(34<='2 · Seu Número'!$C$8,D40-E40,"") | G40: =IF(34<='2 · Seu Número'!$C$8,MAX($F$4-D40,0),"") | H40: =IF(34<='2 · Seu Número'!$C$8,IF(C40="","",IF(D40>=$F$4,"Reserva completa!",IF(F40>=0,"No ritmo","Abaixo da meta"))),"")
B41: 35 | D41: =IF(35<='2 · Seu Número'!$C$8,$D$4+SUM($C$7:C41),"") | E41: =IF(35<='2 · Seu Número'!$C$8,$D$4+'2 · Seu Número'!$C$14*B41,"") | F41: =IF(35<='2 · Seu Número'!$C$8,D41-E41,"") | G41: =IF(35<='2 · Seu Número'!$C$8,MAX($F$4-D41,0),"") | H41: =IF(35<='2 · Seu Número'!$C$8,IF(C41="","",IF(D41>=$F$4,"Reserva completa!",IF(F41>=0,"No ritmo","Abaixo da meta"))),"")
B42: 36 | D42: =IF(36<='2 · Seu Número'!$C$8,$D$4+SUM($C$7:C42),"") | E42: =IF(36<='2 · Seu Número'!$C$8,$D$4+'2 · Seu Número'!$C$14*B42,"") | F42: =IF(36<='2 · Seu Número'!$C$8,D42-E42,"") | G42: =IF(36<='2 · Seu Número'!$C$8,MAX($F$4-D42,0),"") | H42: =IF(36<='2 · Seu Número'!$C$8,IF(C42="","",IF(D42>=$F$4,"Reserva completa!",IF(F42>=0,"No ritmo","Abaixo da meta"))),"")
B43: 37 | D43: =IF(37<='2 · Seu Número'!$C$8,$D$4+SUM($C$7:C43),"") | E43: =IF(37<='2 · Seu Número'!$C$8,$D$4+'2 · Seu Número'!$C$14*B43,"") | F43: =IF(37<='2 · Seu Número'!$C$8,D43-E43,"") | G43: =IF(37<='2 · Seu Número'!$C$8,MAX($F$4-D43,0),"") | H43: =IF(37<='2 · Seu Número'!$C$8,IF(C43="","",IF(D43>=$F$4,"Reserva completa!",IF(F43>=0,"No ritmo","Abaixo da meta"))),"")
B44: 38 | D44: =IF(38<='2 · Seu Número'!$C$8,$D$4+SUM($C$7:C44),"") | E44: =IF(38<='2 · Seu Número'!$C$8,$D$4+'2 · Seu Número'!$C$14*B44,"") | F44: =IF(38<='2 · Seu Número'!$C$8,D44-E44,"") | G44: =IF(38<='2 · Seu Número'!$C$8,MAX($F$4-D44,0),"") | H44: =IF(38<='2 · Seu Número'!$C$8,IF(C44="","",IF(D44>=$F$4,"Reserva completa!",IF(F44>=0,"No ritmo","Abaixo da meta"))),"")
B45: 39 | D45: =IF(39<='2 · Seu Número'!$C$8,$D$4+SUM($C$7:C45),"") | E45: =IF(39<='2 · Seu Número'!$C$8,$D$4+'2 · Seu Número'!$C$14*B45,"") | F45: =IF(39<='2 · Seu Número'!$C$8,D45-E45,"") | G45: =IF(39<='2 · Seu Número'!$C$8,MAX($F$4-D45,0),"") | H45: =IF(39<='2 · Seu Número'!$C$8,IF(C45="","",IF(D45>=$F$4,"Reserva completa!",IF(F45>=0,"No ritmo","Abaixo da meta"))),"")
B46: 40 | D46: =IF(40<='2 · Seu Número'!$C$8,$D$4+SUM($C$7:C46),"") | E46: =IF(40<='2 · Seu Número'!$C$8,$D$4+'2 · Seu Número'!$C$14*B46,"") | F46: =IF(40<='2 · Seu Número'!$C$8,D46-E46,"") | G46: =IF(40<='2 · Seu Número'!$C$8,MAX($F$4-D46,0),"") | H46: =IF(40<='2 · Seu Número'!$C$8,IF(C46="","",IF(D46>=$F$4,"Reserva completa!",IF(F46>=0,"No ritmo","Abaixo da meta"))),"")
B47: 41 | D47: =IF(41<='2 · Seu Número'!$C$8,$D$4+SUM($C$7:C47),"") | E47: =IF(41<='2 · Seu Número'!$C$8,$D$4+'2 · Seu Número'!$C$14*B47,"") | F47: =IF(41<='2 · Seu Número'!$C$8,D47-E47,"") | G47: =IF(41<='2 · Seu Número'!$C$8,MAX($F$4-D47,0),"") | H47: =IF(41<='2 · Seu Número'!$C$8,IF(C47="","",IF(D47>=$F$4,"Reserva completa!",IF(F47>=0,"No ritmo","Abaixo da meta"))),"")
B48: 42 | D48: =IF(42<='2 · Seu Número'!$C$8,$D$4+SUM($C$7:C48),"") | E48: =IF(42<='2 · Seu Número'!$C$8,$D$4+'2 · Seu Número'!$C$14*B48,"") | F48: =IF(42<='2 · Seu Número'!$C$8,D48-E48,"") | G48: =IF(42<='2 · Seu Número'!$C$8,MAX($F$4-D48,0),"") | H48: =IF(42<='2 · Seu Número'!$C$8,IF(C48="","",IF(D48>=$F$4,"Reserva completa!",IF(F48>=0,"No ritmo","Abaixo da meta"))),"")
B49: 43 | D49: =IF(43<='2 · Seu Número'!$C$8,$D$4+SUM($C$7:C49),"") | E49: =IF(43<='2 · Seu Número'!$C$8,$D$4+'2 · Seu Número'!$C$14*B49,"") | F49: =IF(43<='2 · Seu Número'!$C$8,D49-E49,"") | G49: =IF(43<='2 · Seu Número'!$C$8,MAX($F$4-D49,0),"") | H49: =IF(43<='2 · Seu Número'!$C$8,IF(C49="","",IF(D49>=$F$4,"Reserva completa!",IF(F49>=0,"No ritmo","Abaixo da meta"))),"")
B50: 44 | D50: =IF(44<='2 · Seu Número'!$C$8,$D$4+SUM($C$7:C50),"") | E50: =IF(44<='2 · Seu Número'!$C$8,$D$4+'2 · Seu Número'!$C$14*B50,"") | F50: =IF(44<='2 · Seu Número'!$C$8,D50-E50,"") | G50: =IF(44<='2 · Seu Número'!$C$8,MAX($F$4-D50,0),"") | H50: =IF(44<='2 · Seu Número'!$C$8,IF(C50="","",IF(D50>=$F$4,"Reserva completa!",IF(F50>=0,"No ritmo","Abaixo da meta"))),"")
B51: 45 | D51: =IF(45<='2 · Seu Número'!$C$8,$D$4+SUM($C$7:C51),"") | E51: =IF(45<='2 · Seu Número'!$C$8,$D$4+'2 · Seu Número'!$C$14*B51,"") | F51: =IF(45<='2 · Seu Número'!$C$8,D51-E51,"") | G51: =IF(45<='2 · Seu Número'!$C$8,MAX($F$4-D51,0),"") | H51: =IF(45<='2 · Seu Número'!$C$8,IF(C51="","",IF(D51>=$F$4,"Reserva completa!",IF(F51>=0,"No ritmo","Abaixo da meta"))),"")
B52: 46 | D52: =IF(46<='2 · Seu Número'!$C$8,$D$4+SUM($C$7:C52),"") | E52: =IF(46<='2 · Seu Número'!$C$8,$D$4+'2 · Seu Número'!$C$14*B52,"") | F52: =IF(46<='2 · Seu Número'!$C$8,D52-E52,"") | G52: =IF(46<='2 · Seu Número'!$C$8,MAX($F$4-D52,0),"") | H52: =IF(46<='2 · Seu Número'!$C$8,IF(C52="","",IF(D52>=$F$4,"Reserva completa!",IF(F52>=0,"No ritmo","Abaixo da meta"))),"")
B53: 47 | D53: =IF(47<='2 · Seu Número'!$C$8,$D$4+SUM($C$7:C53),"") | E53: =IF(47<='2 · Seu Número'!$C$8,$D$4+'2 · Seu Número'!$C$14*B53,"") | F53: =IF(47<='2 · Seu Número'!$C$8,D53-E53,"") | G53: =IF(47<='2 · Seu Número'!$C$8,MAX($F$4-D53,0),"") | H53: =IF(47<='2 · Seu Número'!$C$8,IF(C53="","",IF(D53>=$F$4,"Reserva completa!",IF(F53>=0,"No ritmo","Abaixo da meta"))),"")
B54: 48 | D54: =IF(48<='2 · Seu Número'!$C$8,$D$4+SUM($C$7:C54),"") | E54: =IF(48<='2 · Seu Número'!$C$8,$D$4+'2 · Seu Número'!$C$14*B54,"") | F54: =IF(48<='2 · Seu Número'!$C$8,D54-E54,"") | G54: =IF(48<='2 · Seu Número'!$C$8,MAX($F$4-D54,0),"") | H54: =IF(48<='2 · Seu Número'!$C$8,IF(C54="","",IF(D54>=$F$4,"Reserva completa!",IF(F54>=0,"No ritmo","Abaixo da meta"))),"")
B55: 49 | D55: =IF(49<='2 · Seu Número'!$C$8,$D$4+SUM($C$7:C55),"") | E55: =IF(49<='2 · Seu Número'!$C$8,$D$4+'2 · Seu Número'!$C$14*B55,"") | F55: =IF(49<='2 · Seu Número'!$C$8,D55-E55,"") | G55: =IF(49<='2 · Seu Número'!$C$8,MAX($F$4-D55,0),"") | H55: =IF(49<='2 · Seu Número'!$C$8,IF(C55="","",IF(D55>=$F$4,"Reserva completa!",IF(F55>=0,"No ritmo","Abaixo da meta"))),"")
B56: 50 | D56: =IF(50<='2 · Seu Número'!$C$8,$D$4+SUM($C$7:C56),"") | E56: =IF(50<='2 · Seu Número'!$C$8,$D$4+'2 · Seu Número'!$C$14*B56,"") | F56: =IF(50<='2 · Seu Número'!$C$8,D56-E56,"") | G56: =IF(50<='2 · Seu Número'!$C$8,MAX($F$4-D56,0),"") | H56: =IF(50<='2 · Seu Número'!$C$8,IF(C56="","",IF(D56>=$F$4,"Reserva completa!",IF(F56>=0,"No ritmo","Abaixo da meta"))),"")
B57: 51 | D57: =IF(51<='2 · Seu Número'!$C$8,$D$4+SUM($C$7:C57),"") | E57: =IF(51<='2 · Seu Número'!$C$8,$D$4+'2 · Seu Número'!$C$14*B57,"") | F57: =IF(51<='2 · Seu Número'!$C$8,D57-E57,"") | G57: =IF(51<='2 · Seu Número'!$C$8,MAX($F$4-D57,0),"") | H57: =IF(51<='2 · Seu Número'!$C$8,IF(C57="","",IF(D57>=$F$4,"Reserva completa!",IF(F57>=0,"No ritmo","Abaixo da meta"))),"")
B58: 52 | D58: =IF(52<='2 · Seu Número'!$C$8,$D$4+SUM($C$7:C58),"") | E58: =IF(52<='2 · Seu Número'!$C$8,$D$4+'2 · Seu Número'!$C$14*B58,"") | F58: =IF(52<='2 · Seu Número'!$C$8,D58-E58,"") | G58: =IF(52<='2 · Seu Número'!$C$8,MAX($F$4-D58,0),"") | H58: =IF(52<='2 · Seu Número'!$C$8,IF(C58="","",IF(D58>=$F$4,"Reserva completa!",IF(F58>=0,"No ritmo","Abaixo da meta"))),"")
B59: 53 | D59: =IF(53<='2 · Seu Número'!$C$8,$D$4+SUM($C$7:C59),"") | E59: =IF(53<='2 · Seu Número'!$C$8,$D$4+'2 · Seu Número'!$C$14*B59,"") | F59: =IF(53<='2 · Seu Número'!$C$8,D59-E59,"") | G59: =IF(53<='2 · Seu Número'!$C$8,MAX($F$4-D59,0),"") | H59: =IF(53<='2 · Seu Número'!$C$8,IF(C59="","",IF(D59>=$F$4,"Reserva completa!",IF(F59>=0,"No ritmo","Abaixo da meta"))),"")
B60: 54 | D60: =IF(54<='2 · Seu Número'!$C$8,$D$4+SUM($C$7:C60),"") | E60: =IF(54<='2 · Seu Número'!$C$8,$D$4+'2 · Seu Número'!$C$14*B60,"") | F60: =IF(54<='2 · Seu Número'!$C$8,D60-E60,"") | G60: =IF(54<='2 · Seu Número'!$C$8,MAX($F$4-D60,0),"") | H60: =IF(54<='2 · Seu Número'!$C$8,IF(C60="","",IF(D60>=$F$4,"Reserva completa!",IF(F60>=0,"No ritmo","Abaixo da meta"))),"")
B61: 55 | D61: =IF(55<='2 · Seu Número'!$C$8,$D$4+SUM($C$7:C61),"") | E61: =IF(55<='2 · Seu Número'!$C$8,$D$4+'2 · Seu Número'!$C$14*B61,"") | F61: =IF(55<='2 · Seu Número'!$C$8,D61-E61,"") | G61: =IF(55<='2 · Seu Número'!$C$8,MAX($F$4-D61,0),"") | H61: =IF(55<='2 · Seu Número'!$C$8,IF(C61="","",IF(D61>=$F$4,"Reserva completa!",IF(F61>=0,"No ritmo","Abaixo da meta"))),"")
B62: 56 | D62: =IF(56<='2 · Seu Número'!$C$8,$D$4+SUM($C$7:C62),"") | E62: =IF(56<='2 · Seu Número'!$C$8,$D$4+'2 · Seu Número'!$C$14*B62,"") | F62: =IF(56<='2 · Seu Número'!$C$8,D62-E62,"") | G62: =IF(56<='2 · Seu Número'!$C$8,MAX($F$4-D62,0),"") | H62: =IF(56<='2 · Seu Número'!$C$8,IF(C62="","",IF(D62>=$F$4,"Reserva completa!",IF(F62>=0,"No ritmo","Abaixo da meta"))),"")
B63: 57 | D63: =IF(57<='2 · Seu Número'!$C$8,$D$4+SUM($C$7:C63),"") | E63: =IF(57<='2 · Seu Número'!$C$8,$D$4+'2 · Seu Número'!$C$14*B63,"") | F63: =IF(57<='2 · Seu Número'!$C$8,D63-E63,"") | G63: =IF(57<='2 · Seu Número'!$C$8,MAX($F$4-D63,0),"") | H63: =IF(57<='2 · Seu Número'!$C$8,IF(C63="","",IF(D63>=$F$4,"Reserva completa!",IF(F63>=0,"No ritmo","Abaixo da meta"))),"")
B64: 58 | D64: =IF(58<='2 · Seu Número'!$C$8,$D$4+SUM($C$7:C64),"") | E64: =IF(58<='2 · Seu Número'!$C$8,$D$4+'2 · Seu Número'!$C$14*B64,"") | F64: =IF(58<='2 · Seu Número'!$C$8,D64-E64,"") | G64: =IF(58<='2 · Seu Número'!$C$8,MAX($F$4-D64,0),"") | H64: =IF(58<='2 · Seu Número'!$C$8,IF(C64="","",IF(D64>=$F$4,"Reserva completa!",IF(F64>=0,"No ritmo","Abaixo da meta"))),"")
B65: 59 | D65: =IF(59<='2 · Seu Número'!$C$8,$D$4+SUM($C$7:C65),"") | E65: =IF(59<='2 · Seu Número'!$C$8,$D$4+'2 · Seu Número'!$C$14*B65,"") | F65: =IF(59<='2 · Seu Número'!$C$8,D65-E65,"") | G65: =IF(59<='2 · Seu Número'!$C$8,MAX($F$4-D65,0),"") | H65: =IF(59<='2 · Seu Número'!$C$8,IF(C65="","",IF(D65>=$F$4,"Reserva completa!",IF(F65>=0,"No ritmo","Abaixo da meta"))),"")
B66: 60 | D66: =IF(60<='2 · Seu Número'!$C$8,$D$4+SUM($C$7:C66),"") | E66: =IF(60<='2 · Seu Número'!$C$8,$D$4+'2 · Seu Número'!$C$14*B66,"") | F66: =IF(60<='2 · Seu Número'!$C$8,D66-E66,"") | G66: =IF(60<='2 · Seu Número'!$C$8,MAX($F$4-D66,0),"") | H66: =IF(60<='2 · Seu Número'!$C$8,IF(C66="","",IF(D66>=$F$4,"Reserva completa!",IF(F66>=0,"No ritmo","Abaixo da meta"))),"")

Sheet 4 · Simulador de prazo
B2: Simulador de prazo
B3: Quanto guardar por mês para chegar ao seu número em cada prazo. Usa os dados da aba 2.
B5: Prazo (meses) | C5: Guardar por mês | D5: Por semana (aprox.) | E5: Por dia (aprox.)
B6: 6 | C6: ='2 · Seu Número'!$C$13/B6 | D6: =C6*12/52 | E6: =C6*12/365
B7: 9 | C7: ='2 · Seu Número'!$C$13/B7 | D7: =C7*12/52 | E7: =C7*12/365
B8: 12 | C8: ='2 · Seu Número'!$C$13/B8 | D8: =C8*12/52 | E8: =C8*12/365
B9: 15 | C9: ='2 · Seu Número'!$C$13/B9 | D9: =C9*12/52 | E9: =C9*12/365
B10: 18 | C10: ='2 · Seu Número'!$C$13/B10 | D10: =C10*12/52 | E10: =C10*12/365
B11: 24 | C11: ='2 · Seu Número'!$C$13/B11 | D11: =C11*12/52 | E11: =C11*12/365
B12: 30 | C12: ='2 · Seu Número'!$C$13/B12 | D12: =C12*12/52 | E12: =C12*12/365
B13: 36 | C13: ='2 · Seu Número'!$C$13/B13 | D13: =C13*12/52 | E13: =C13*12/365
B15: A linha destacada é o prazo que você escolheu na aba 2.
